create_agent_resources_repo/__init__.py
create_agent_resources_repo-0.1.0.dist-info/METADATA
create_agent_resources_repo-0.1.0.dist-info/WHEEL
create_agent_resources_repo-0.1.0.dist-info/entry_points.txt
create_agent_resources_repo-0.1.0.dist-info/RECORD
