Metadata-Version: 2.4
Name: create-agent-resources-repo
Version: 0.1.0
Summary: Create a personal agent-resources repository for Claude Code
License-Expression: MIT
Requires-Python: >=3.10
Requires-Dist: agent-resources>=0.1.0
